mfsr_rcs/__init__.py
mfsr_rcs/fragment_based_chemical_space.py
mfsr_rcs-0.0.2.dist-info/METADATA
mfsr_rcs-0.0.2.dist-info/WHEEL
mfsr_rcs-0.0.2.dist-info/licenses/LICENSE
mfsr_rcs-0.0.2.dist-info/RECORD
