Metadata-Version: 2.1
Name: mfsr_rcs
Version: 0.0.2
Summary: Functions for generating the MFSR and RCS representations.
Project-URL: Homepage, https://github.com/hits-ccc/MFSR_RCSa
Author-email: Stiv Llenga <stiv.llenga@h-its.org>
License-File: LICENSE
Classifier: License :: OSI Approved :: MIT License
Classifier: Operating System :: OS Independent
Classifier: Programming Language :: Python :: 3
Requires-Python: >=3.7
